voliboli_pdf_scraper/__init__.py
voliboli_pdf_scraper/constants.py
voliboli_pdf_scraper/main.py
voliboli_pdf_scraper-1.8.dist-info/LICENSE.md
voliboli_pdf_scraper-1.8.dist-info/METADATA
voliboli_pdf_scraper-1.8.dist-info/WHEEL
voliboli_pdf_scraper-1.8.dist-info/top_level.txt
voliboli_pdf_scraper-1.8.dist-info/RECORD
