Metadata-Version: 2.1
Name: voliboli_pdf_scraper
Version: 1.8
Summary: Voliboli PDF Scraper
Author: Teodor Janez Podobnik
Author-email: teo.podobnik1234@gmail.com
License: MIT
Classifier: Programming Language :: Python :: 3
Classifier: License :: OSI Approved :: MIT License
Classifier: Operating System :: OS Independent
License-File: LICENSE.md
Requires-Dist: tabula-py
Requires-Dist: numpy
